lib/libflipro.h
lib/liblibflialgo.so
lib/liblibflipro.so
pyobs_flipro-1.2.0.dist-info/METADATA
pyobs_flipro-1.2.0.dist-info/WHEEL
pyobs_flipro-1.2.0.dist-info/licenses/LICENSE
pyobs_flipro-1.2.0.dist-info/RECORD
